vcxproj.py
vcxproj_stream_editor-0.1.0.dist-info/METADATA
vcxproj_stream_editor-0.1.0.dist-info/WHEEL
vcxproj_stream_editor-0.1.0.dist-info/top_level.txt
vcxproj_stream_editor-0.1.0.dist-info/RECORD
