Metadata-Version: 2.1
Name: vcxproj-stream-editor
Version: 0.1.0
Summary: Rewrite Visual Studio .vcxproj files without spurious changes
Author: Mark A. Tsuchida, contributors
Project-URL: Repository, https://github.com/marktsuchida/vcxproj-stream-editor
Keywords: Visual Studio,MSBuild,vcxproj,project,XML
Classifier: License :: OSI Approved :: MIT License
Classifier: Programming Language :: Python :: 3
Classifier: Topic :: Software Development
Requires-Python: >=3.3
